request_ssh_certificate/__init__.py
request_ssh_certificate/__main__.py
request_ssh_certificate/cli.py
request_ssh_certificate/py.typed
request_ssh_certificate/request_ssh_certificate.py
request_ssh_certificate-1.0.1.dist-info/LICENSE
request_ssh_certificate-1.0.1.dist-info/METADATA
request_ssh_certificate-1.0.1.dist-info/WHEEL
request_ssh_certificate-1.0.1.dist-info/entry_points.txt
request_ssh_certificate-1.0.1.dist-info/top_level.txt
request_ssh_certificate-1.0.1.dist-info/RECORD
