Metadata-Version: 2.1
Name: request_ssh_certificate
Version: 1.0.1
Summary: Request a SSH certificate from a lambda
Home-page: https://github.com/TheToddLuci0/request_ssh_certificate
Author: TheToddLuci0
Author-email: email@example.com
License: MIT license
Keywords: request_ssh_certificate
Classifier: Development Status :: 2 - Pre-Alpha
Classifier: License :: OSI Approved :: MIT License
Classifier: Natural Language :: English
Classifier: Programming Language :: Python :: 3
Requires-Python: >=3.6
License-File: LICENSE
Requires-Dist: boto3
